{
  "subject": "Project Management",
  "subjectCode": "SBU 405D",
  "academicYear": "2020/2021",
  "semesters": [
    {
      "semester": "Semester I",
      "sectionA": [
        {
          "type": "single",
          "question": "Advertising, shipping and utilities are examples of project overhead cost.",
          "options": [
            "A. False",
            "B. True"
          ],
          "correctAnswer": "B",
          "explanation": "Advertising and shipping are examples of selling and administration costs, while utilities are an example of overhead cost, both of which are indirect costs or overheads.",
          "reference": "Unit 2, Session 2, 2.1.2 - Indirect costs"
        },
        {
          "type": "single",
          "question": "The process of tracking team member performance, providing feedback, resolving issues and managing team changes to optimize project performance is referred to as ______.",
          "options": [
            "A. Human resource management",
            "B. Project team management",
            "C. Project team development",
            "D. Project team acquisition"
          ],
          "correctAnswer": "B",
          "explanation": "Project team management is the process of tracking team member performance, providing feedback, resolving issues, and managing team changes to optimize project performance.",
          "reference": "Unit 4, Session 1, (The Human resource management activities)"
        },
        {
          "type": "single",
          "question": "Which of the following stages clearly explain the processes involved in developing the human resource plan for a project?\nI. Specify the skill requirement\nII. Identify and document project roles and responsibilities\nIII. Establish reporting relationships\nIV. Create staffing management plan",
          "options": [
            "A. I, III, IV and II",
            "B. II, I, III and IV",
            "C. III, IV, II and I",
            "D. I, II, III and IV"
          ],
          "correctAnswer": "B",
          "explanation": "The human resource management plan is developed in a specific order: 1) Identify roles, 2) Specify skills, 3) Establish reporting relationships, and 4) Create a staffing management plan.",
          "reference": "Unit 4, Session 2, 2.1 - Plan Human Resource Management"
        },
        {
          "type": "single",
          "question": "Managing human resource of a project helps in the following ways except ______.",
          "options": [
            "A. creating teams that are unsupportive of each other",
            "B. it gives the ability to resolve employee complaints",
            "C. it helps in knowing when and how team members should be added",
            "D. identifying and engaging employees with a variety of skill levels"
          ],
          "correctAnswer": "A",
          "explanation": "Managing human resources helps construct a team that supports and complements each other, not one that is unsupportive. The other options are listed as benefits.",
          "reference": "Unit 4, Session 1, 6.3 - Importance of Project Human Resource Management"
        },
        {
          "type": "single",
          "question": "Which of the following skills of a manager allow him/her to visualize the entire organisation and work with ideas and the relationships between abstract concepts?",
          "options": [
            "A. Abstract skills",
            "B. Conceptual skills",
            "C. Human skills",
            "D. Technical skills"
          ],
          "correctAnswer": "B",
          "explanation": "Conceptual skills allow a manager to visualize the entire organization and work with ideas and the relationships between abstract concepts.",
          "reference": "Unit 4, Session 2, 2.1.2 - Specify skills requirement"
        },
        {
          "type": "single",
          "question": "Unplanned costs incurred when steps are taken to speed up the project's completion are referred to as ______.",
          "options": [
            "A. Expedited Costs",
            "B. Fixed Costs",
            "C. Variable Costs",
            "D. Normal Costs"
          ],
          "correctAnswer": "A",
          "explanation": "Expedited costs are unplanned costs incurred when steps are taken to speed up the project's completion, such as overtime or hiring additional workers.",
          "reference": "Unit 2, Session 2, 2.1.8 - Expedited costs"
        },
        {
          "type": "single",
          "question": "Business angels, are examples of short-term project funding sources.",
          "options": [
            "A. False",
            "B. True"
          ],
          "correctAnswer": "A",
          "explanation": "Business angels are private investors who invest directly in a company, typically for the long-term, and are classified as a source of long-term project funding.",
          "reference": "Unit 2, Session 4, 4.3.3 - Business Angels"
        },
        {
          "type": "single",
          "question": "Which of the following is not an example of long-term sources of project funding?",
          "options": [
            "A. Venture Capital",
            "B. Bank overdraft",
            "C. Retained Profits",
            "D. Share Capital"
          ],
          "correctAnswer": "B",
          "explanation": "Bank overdrafts are a source of short-term finance, as they are typically due for repayment in less than a year. The others are all long-term sources.",
          "reference": "Unit 2, Session 4, 4.2.1 - Bank Overdrafts; 4.3 - Sources of Long-term Project Funding"
        },
        {
          "type": "single",
          "question": "Which of the classification of procurement risk management are influenced by factors such as seasonality, taxation, product availability and price?",
          "options": [
            "A. Disruption risks",
            "B. Demand fluctuation",
            "C. Uncertain lead time",
            "D. Unreliable yield"
          ],
          "correctAnswer": "B",
          "explanation": "Demand fluctuation is highly probable due to factors that influence demand, including seasonality, taxation, product availability, and price.",
          "reference": "Unit 2, Session 6, 6.2.1 - Demand fluctuation"
        },
        {
          "type": "single",
          "question": "Project termination type where the needed resources to execute the project are either lacking or inadequately available is referred to as ______.",
          "options": [
            "A. Project starvation",
            "B. Termination by extinction",
            "C. Termination by addition",
            "D. Termination by integration"
          ],
          "correctAnswer": "A",
          "explanation": "Project starvation occurs when the needed resources needed by the project organization to execute the project is lacking or inadequate or unavailable.",
          "reference": "Unit 1, Session 5, 5.1.2 - Project Termination/Closure"
        },
        {
          "type": "single",
          "question": "Project vision conflicts arise due to the differences in stakeholders' opinion and understanding of the overall outcome of the project.",
          "options": [
            "A. False",
            "B. True"
          ],
          "correctAnswer": "B",
          "explanation": "Project vision conflicts are specifically defined as arising from differences in stakeholders' opinion and understanding of the vision and overall outcome of the project.",
          "reference": "Unit 1, Session 4, 4.2.1 - Project Vision"
        },
        {
          "type": "single",
          "question": "The conflict resolution approach where the person involved either physically or psychologically removes himself or herself from the conflict is referred to as ______.",
          "options": [
            "A. Accommodation",
            "B. Avoidance",
            "C. Compromise",
            "D. Competition"
          ],
          "correctAnswer": "B",
          "explanation": "Avoidance is defined as physically or psychologically removing oneself from the conflict, as the parties feel it is hopeless to try and resolve it.",
          "reference": "Unit 1, Session 4, 4.3.1 - Avoidance"
        },
        {
          "type": "single",
          "question": "Which of the following is a key feature of the second phase of the project life cycle?",
          "options": [
            "A. A business case is made for the project",
            "B. Activities are outlined",
            "C. Opportunities are identified",
            "D. Monitoring and controlling deliverables"
          ],
          "correctAnswer": "B",
          "explanation": "The second phase is project planning, which involves the outlining of the activities, tasks, dependencies and timeframes pertaining to the project.",
          "reference": "Unit 1, Session 5, 5.1.2 - Project Planning"
        },
        {
          "type": "single",
          "question": "Project cost associated with hiring and paying the various classification of workers involved in developing the project is classified as a service cost.",
          "options": [
            "A. False",
            "B. True"
          ],
          "correctAnswer": "A",
          "explanation": "Labour costs are costs associated with hiring and paying workers. Service costs are associated with the work done by consultants, experts, and subcontractors.",
          "reference": "Unit 2, Session 1, 1.2.1 - Labour Cost; 1.2.3 - Service Cost"
        },
        {
          "type": "single",
          "question": "Indirect cost associated with a project include the following except ______.",
          "options": [
            "A. advertising",
            "B. depreciation of equipment",
            "C. insurance",
            "D. materials"
          ],
          "correctAnswer": "D",
          "explanation": "Indirect costs include overheads (like insurance, depreciation) and selling/administration costs (like advertising). Materials cost is a direct cost.",
          "reference": "Unit 2, Session 2, 2.1.1 - Direct costs; 2.1.2 - Indirect costs"
        },
        {
          "type": "single",
          "question": "Which of the following is an example of an active stakeholder of a project?",
          "options": [
            "A. Competitors",
            "B. Persons indirectly affected by the project",
            "C. Project coordinators",
            "D. Public authorities"
          ],
          "correctAnswer": "C",
          "explanation": "Active stakeholders are those directly involved in the project, such as the project team, project manager, and project coordinators. The other options are passive types.",
          "reference": "Unit 1, Session 1, 1.4 - Starting and Ending a Project."
        },
        {
          "type": "single",
          "question": "Which of the following is generally considered as a project?",
          "options": [
            "A. An organisation that strives to stay afloat",
            "B. Conducting research whose outcome is recorded",
            "C. Managing a product",
            "D. Protecting an organisations sales territory"
          ],
          "correctAnswer": "B",
          "explanation": "A project is a temporary endeavor to create a unique product, service, or result. Conducting research to produce a documented outcome (a result) fits this definition.",
          "reference": "Unit 1, Session 1, 1.1 - What is Project"
        },
        {
          "type": "single",
          "question": "Scope, cost and risk are the most important traditional constraints of project management.",
          "options": [
            "A. False",
            "B. True"
          ],
          "correctAnswer": "A",
          "explanation": "The three most important traditional constraints are time (schedule), cost (budget), and scope. Risk is an additional modern constraint, not one of the original three.",
          "reference": "Unit 1, Session 2, 2.4 - Constraints to project Management"
        },
        {
          "type": "single",
          "question": "The responsibilities of the project manager at the organisational level includes the following, except ______.",
          "options": [
            "A. controlling budgets",
            "B. creating overall project plan and forms project team members",
            "C. linking between the strategy and project team",
            "D. sharing progress reports with the sponsors and all stakeholders"
          ],
          "correctAnswer": "A",
          "explanation": "Controlling budgets is a responsibility at the project level, not the organizational level. The other options are listed as organizational-level responsibilities.",
          "reference": "Unit 1, Session 3, 3.4.1 - Responsibilities of the Project Manager"
        },
        {
          "type": "single",
          "question": "Which of the following best describe the interpersonal skills required by project managers?\nI. Leadership\nII. Team building\nIII. Communication\nIV. Building trust",
          "options": [
            "A. I only",
            "B. I and II only",
            "C. I, II, III only",
            "D. I, II, III and IV"
          ],
          "correctAnswer": "D",
          "explanation": "The text lists leadership, team building, motivation, communication, influencing, decision making, political awareness, negotiation, trust building, conflict management, and coaching as interpersonal skills.",
          "reference": "Unit 1, Session 3, 3.4.3 - Interpersonal Skills of a Project Manager"
        }
      ],
      "sectionB": {
        "format": "grouped",
        "questions": [
          {
            "label": "Question 1",
            "totalMarks": 20,
            "subQuestions": [
              {
                "label": "a",
                "question": "Using relevant examples, explain the four main classifications of project delay types.",
                "marks": 10,
                "commandWord": "Explain",
                "answer": {
                  "introduction": "Project delays can be classified into four main types based on their impact, controllability, and compensability.",
                  "mainPoints": [
                    {
                      "heading": "Critical or Non-critical Delays",
                      "detail": "A critical delay extends the project's overall duration, leading to increased costs (e.g., a delay in pouring the foundation of a building pushes back the entire construction schedule). A non-critical delay does not extend the overall project but affects individual activity timelines (e.g., painting a room can be delayed without affecting the final move-in date if there is slack time)."
                    },
                    {
                      "heading": "Excusable or Non-excusable Delays",
                      "detail": "An excusable delay is beyond the project team's control, like a natural disaster (e.g., a flood delaying site work). A non-excusable delay is the project team's fault, such as delayed procurement of materials (e.g., the project manager ordering steel beams too late)."
                    },
                    {
                      "heading": "Concurrent Delays",
                      "detail": "This occurs when two or more delays happen at the same time, affecting project completion (e.g., a strike by workers happening at the same time as a delay in client approvals for a design change)."
                    },
                    {
                      "heading": "Compensable or Non-compensable Delays",
                      "detail": "A compensable delay entitles the contractor to both a time extension and cost compensation, typically caused by the client (e.g., the client asking for a major design change). A non-compensable delay is solely the contractor's fault, and they bear all costs and liabilities (e.g., the contractor using unskilled labor that slows down work)."
                    }
                  ],
                  "conclusion": "Understanding these classifications helps in assigning responsibility and determining the appropriate contractual remedies for project delays.",
                  "otherPossibleAnswers": "N/A",
                  "reference": "Unit 1, Session 6, 6.2 - Types of Delays in Projects"
                }
              },
              {
                "label": "b",
                "question": "Examine five causes of delays in projects.",
                "marks": 10,
                "commandWord": "Examine",
                "answer": {
                  "introduction": "Project delays can stem from various sources, ranging from planning errors to external factors, all of which can impact the project's timeline and cost.",
                  "mainPoints": [
                    {
                      "heading": "Design Errors",
                      "detail": "Errors in project design lead to wrong application of techniques, cost overruns, and the need for additional work and change orders, which cause significant delays."
                    },
                    {
                      "heading": "Scope Change",
                      "detail": "Any change in project scope during execution forces a review of the entire project plan, including budget and schedule, leading to delays while new baselines are developed."
                    },
                    {
                      "heading": "Inappropriate Procurement and Faulty Contractual Management",
                      "detail": "Poor selection of contractors and ambiguous contracts can lead to disputes, long chains of negotiation, and arbitration, all of which stall project progress."
                    },
                    {
                      "heading": "Subcontractor and Consultant Delays",
                      "detail": "Delays caused by the inability of subcontractors or consultants to complete their work on time are common and often difficult for the main organization to control."
                    },
                    {
                      "heading": "Client-End Delays",
                      "detail": "Delays can result from client dissatisfaction, requests for alterations, or a client changing their mind about project requirements, often requiring contract renegotiation."
                    }
                  ],
                  "conclusion": "Identifying these potential causes early in the project can help in developing proactive mitigation strategies to keep the project on schedule.",
                  "otherPossibleAnswers": "Complexity of the project, Post Execution Phase (Closure) issues, Shipping and Supply Delays, Climate Delays.",
                  "reference": "Unit 1, Session 6, 6.3 - Causes of Project Delays"
                }
              }
            ]
          },
          {
            "label": "Question 2",
            "totalMarks": 20,
            "subQuestions": [
              {
                "label": "a",
                "question": "Analyse the processes involved in project procurement management.",
                "marks": 12,
                "commandWord": "Analyse",
                "answer": {
                  "introduction": "Project procurement management involves a series of interconnected processes to acquire goods and services from outside the project organization.",
                  "mainPoints": [
                    {
                      "heading": "Procurement Planning",
                      "detail": "The initial process of identifying which project needs can best be met by procuring products or services externally, considering what is available in the marketplace and making \"make-or-buy\" decisions."
                    },
                    {
                      "heading": "Solicitation Planning",
                      "detail": "This stage involves documenting product requirements and identifying potential sources. It includes preparing solicitation documents like Requests for Proposal (RFP) and defining the evaluation criteria for sellers."
                    },
                    {
                      "heading": "Solicitation",
                      "detail": "This is the process of obtaining bids and proposals from prospective sellers. Activities include sending out procurement documents and holding bidder conferences to ensure all sellers have a clear understanding of the requirements."
                    },
                    {
                      "heading": "Source Selection",
                      "detail": "The process of evaluating proposals and bids using predefined criteria. Proposals are often scored and ranked, and the highest-ranked seller is selected for contract negotiation."
                    },
                    {
                      "heading": "Contract Administration",
                      "detail": "This stage ensures that the seller's performance meets the contractual requirements. It involves applying project management processes to the contractual relationship and managing changes, payments, and quality control."
                    },
                    {
                      "heading": "Contract Closeout",
                      "detail": "The final process of completing and settling the contract, including confirming that all work and deliverables were accepted and resolving any open items. It involves updating records and documenting lessons learned."
                    }
                  ],
                  "conclusion": "Following these structured processes ensures that procurement is conducted fairly, transparently, and in a way that best serves the project's objectives.",
                  "otherPossibleAnswers": "N/A",
                  "reference": "Unit 2, Session 5, 5.2 - Procurement Process"
                }
              },
              {
                "label": "b",
                "question": "Examine any four main risks that occur in project procurement process.",
                "marks": 8,
                "commandWord": "Examine",
                "answer": {
                  "introduction": "The procurement process is exposed to various risks that can disrupt the project's supply chain and affect its cost and schedule.",
                  "mainPoints": [
                    {
                      "heading": "Demand fluctuation",
                      "detail": "Uncertainty in demand for project materials or services can affect cost and schedule. Factors like seasonality and price changes make it hard to order the correct quantity, potentially leading to shortages or waste."
                    },
                    {
                      "heading": "Vague price information",
                      "detail": "Instability in the market price of materials and services creates uncertainty. Different purchasing times mean different costs, making budget planning difficult."
                    },
                    {
                      "heading": "Unreliable yield",
                      "detail": "This risk stems from a supplier's limited production capability or inability to meet product requirements. It can lead to shortages of critical materials, forcing the project to find alternative, potentially more expensive, sources."
                    },
                    {
                      "heading": "Uncertain lead time",
                      "detail": "Unpredictable time between placing an order and receiving it can disrupt project scheduling. If lead times are uncertain, it's difficult to plan activities, and delays can increase total project costs."
                    }
                  ],
                  "conclusion": "Effectively managing these procurement risks through strategies like supplier diversification and financial hedging is crucial for project stability.",
                  "otherPossibleAnswers": "Disruption risks, Multiple uncertainties.",
                  "reference": "Unit 2, Session 6, 6.2 - Classification of Procurement Risk Management"
                }
              }
            ]
          },
          {
            "label": "Question 3",
            "totalMarks": 20,
            "subQuestions": [
              {
                "label": "a",
                "question": "Examine two importance and challenges each of project communication management.",
                "marks": 8,
                "commandWord": "Examine",
                "answer": {
                  "introduction": "Project communication management is vital for project success, but it also presents several challenges that must be navigated.",
                  "mainPoints": [
                    {
                      "heading": "Importance 1: Relay of Information",
                      "detail": "It ensures the right information is sent to the right people through the right media, facilitating the flow of progress reports and updates to stakeholders."
                    },
                    {
                      "heading": "Importance 2: Clarifies Tasks",
                      "detail": "It ensures all project teams have their tasks communicated clearly, giving team members a clear understanding of the creative skills and work expected of them."
                    },
                    {
                      "heading": "Challenge 1: Poor Communication as an Excuse",
                      "detail": "When issues arise, \"poor communication\" is often used as an excuse, which stems from a failure to dynamically integrate formal and informal communication plans."
                    },
                    {
                      "heading": "Challenge 2: Unclear Definition of Objectives",
                      "detail": "If project goals and purpose are not clearly communicated from the start, it leads to confusion and chaos among team members and stakeholders."
                    }
                  ],
                  "conclusion": "Effective communication management requires a well-followed plan to reap its benefits and avoid the pitfalls of misunderstanding and misinformation.",
                  "otherPossibleAnswers": "Importance: Intensifies the effectiveness of everyone the project manager interacts with. Challenges: Language barriers in global projects.",
                  "reference": "Unit 4, Session 4, 4.3 - Importance of Project Communication Management; 4.4 - Challenges in Communication Management"
                }
              },
              {
                "label": "b",
                "question": "Explain the activities involved in the project integration management process.",
                "marks": 12,
                "commandWord": "Explain",
                "answer": {
                  "introduction": "Project integration management involves a series of interconnected activities that unify and coordinate all aspects of a project throughout its life cycle.",
                  "mainPoints": [
                    {
                      "heading": "Develop Project Charter",
                      "detail": "The process of creating a document that formally authorizes the project and gives the project manager authority to apply organizational resources to project activities."
                    },
                    {
                      "heading": "Develop Project Management Plan",
                      "detail": "The process of defining, preparing, and coordinating all subsidiary plans and baselines into a comprehensive project management plan that guides execution, monitoring, and closure."
                    },
                    {
                      "heading": "Direct and Manage Project Work",
                      "detail": "The process of leading and performing the work defined in the project management plan and implementing approved changes to achieve the project's objectives."
                    },
                    {
                      "heading": "Monitor and Control Project Work",
                      "detail": "The process of tracking, reviewing, and reporting overall project progress to meet performance objectives defined in the project management plan."
                    },
                    {
                      "heading": "Perform Integrated Change Control",
                      "detail": "The process of reviewing all change requests, approving and managing changes to deliverables, project documents, and the project management plan, and communicating their disposition."
                    },
                    {
                      "heading": "Close Project or Phase",
                      "detail": "The process of finalizing all activities across all Project Management Process Groups to formally complete the project or phase."
                    }
                  ],
                  "conclusion": "These integration activities ensure that all elements of the project are properly coordinated, from initial authorization to final closure.",
                  "otherPossibleAnswers": "N/A",
                  "reference": "Unit 5, Session 1, 1.1 - The Project Integration Management Process or Activities; Sessions 2 and 3"
                }
              }
            ]
          },
          {
            "label": "Question 4",
            "totalMarks": 20,
            "subQuestions": [
              {
                "label": "a",
                "question": "Examine four common problems associated with project scope management.",
                "marks": 10,
                "commandWord": "Examine",
                "answer": {
                  "introduction": "Common problems in project scope management can derail a project, leading to delays, cost overruns, and stakeholder dissatisfaction.",
                  "mainPoints": [
                    {
                      "heading": "Ambiguity",
                      "detail": "A vague or unclear scope leads to unnecessary work, confusion among team members, and misinterpretations of requirements."
                    },
                    {
                      "heading": "Incomplete definition",
                      "detail": "An incomplete scope fails to capture all necessary work, leading to schedule slips and cost overruns as missing elements are discovered later."
                    },
                    {
                      "heading": "Transience (Scope Creep)",
                      "detail": "A scope that is not finalized and is constantly changed leads to \"scope creep,\" which is a primary cause of late deliveries and projects that never seem to end."
                    },
                    {
                      "heading": "Uncollaborated scope",
                      "detail": "A scope developed in isolation without input from all key stakeholders causes misinterpretations in requirements and design, as it doesn't reflect everyone's needs."
                    }
                  ],
                  "conclusion": "Addressing these issues through clear, complete, stable, and collaborative scope definition is critical for project success.",
                  "otherPossibleAnswers": "Poor scope change management can lead to disputes and arbitration, causing further delays.",
                  "reference": "Unit 3, Session 1, (Common problems associated with project scope management)"
                }
              },
              {
                "label": "b",
                "question": "Explain four importance of time management in projects.",
                "marks": 10,
                "commandWord": "Explain",
                "answer": {
                  "introduction": "Project time management is a critical knowledge area, as it directly influences the project's ability to meet its deadlines and be perceived as successful.",
                  "mainPoints": [
                    {
                      "heading": "Provides assurance of project success",
                      "detail": "Meeting the scheduled date is a key indicator of project success. Time management ensures projects do not go beyond the scheduled time, which would be viewed as failure."
                    },
                    {
                      "heading": "Results in effectiveness and efficiency",
                      "detail": "When time is managed well, activities are performed within the planned duration, leading to both effectiveness (doing the right things) and efficiency (doing things right)."
                    },
                    {
                      "heading": "Reduces stress",
                      "detail": "Proper time management prevents unnecessary delays and ensures work progresses as expected, which reduces project-related stress for the team and stakeholders."
                    },
                    {
                      "heading": "Results in quality output",
                      "detail": "By ensuring work is done based on the time scheduled, project time management helps maintain a steady pace and focus, which contributes to meeting the set quality standards."
                    }
                  ],
                  "conclusion": "Effective time management is essential not just for finishing on time, but for maintaining team morale, controlling costs, and delivering quality results.",
                  "otherPossibleAnswers": "N/A",
                  "reference": "Unit 3, Session 4, (Importance of Time Management)"
                }
              }
            ]
          }
        ]
      }
    }
  ]
}
